gajou_cli/__init__.py
gajou_cli/base_cli.py
gajou_cli/cli_response.py
gajou_cli/return_codes.py
gajou_cli-0.1.8.dist-info/LICENSE
gajou_cli-0.1.8.dist-info/METADATA
gajou_cli-0.1.8.dist-info/WHEEL
gajou_cli-0.1.8.dist-info/top_level.txt
gajou_cli-0.1.8.dist-info/RECORD
